crash_mapping_tools/__init__.py
crash_mapping_tools-0.0.2.dist-info/LICENSE
crash_mapping_tools-0.0.2.dist-info/METADATA
crash_mapping_tools-0.0.2.dist-info/WHEEL
crash_mapping_tools-0.0.2.dist-info/entry_points.txt
crash_mapping_tools-0.0.2.dist-info/top_level.txt
crash_mapping_tools-0.0.2.dist-info/RECORD
