Metadata-Version: 2.1
Name: crash-mapping-tools
Version: 0.0.2
Summary: Standalone tools for processing crash data
Author-email: Tyler Eshelman <teshelman@edac.unm.edu>, Hays Barrett <hbarrett@edac.unm.edu>, Eric Crozier <ecrozier@edac.unm.edu>
License: MIT License
Keywords: crash,mapping
Classifier: License :: OSI Approved :: MIT License
Classifier: Programming Language :: Python
Classifier: Programming Language :: Python :: 3
Requires-Python: >=3.7
License-File: LICENSE
Requires-Dist: matplotlib >=3.3.4
Requires-Dist: numpy >=1.19.5
Requires-Dist: KDEpy >=1.1.0
Requires-Dist: geopandas >=0.9.0
Requires-Dist: pyproj >=3.0.1
Requires-Dist: Fiona >=1.8.20
Requires-Dist: scikit-learn >=0.24.2
Requires-Dist: scipy >=1.5.4
Requires-Dist: shapely >=1.7.1
Requires-Dist: geojson >=2.5.0
Requires-Dist: GDAL ==3.4.3
Requires-Dist: pysal
